superlogs/__init__.py
superlogs-0.0.6.dist-info/METADATA
superlogs-0.0.6.dist-info/WHEEL
superlogs-0.0.6.dist-info/top_level.txt
superlogs-0.0.6.dist-info/RECORD
